pechenegi/__init__.py
pechenegi/starting.py
pechenegi/c/1.txt
pechenegi/c/10.txt
pechenegi/c/11.txt
pechenegi/c/12.txt
pechenegi/c/13.txt
pechenegi/c/14.txt
pechenegi/c/15.txt
pechenegi/c/16.txt
pechenegi/c/17.txt
pechenegi/c/18.txt
pechenegi/c/19.txt
pechenegi/c/2.txt
pechenegi/c/20.txt
pechenegi/c/21.txt
pechenegi/c/22.txt
pechenegi/c/23.txt
pechenegi/c/24.txt
pechenegi/c/25.txt
pechenegi/c/26.txt
pechenegi/c/27.txt
pechenegi/c/28.txt
pechenegi/c/29.txt
pechenegi/c/3.txt
pechenegi/c/30.txt
pechenegi/c/31.txt
pechenegi/c/32.txt
pechenegi/c/33.txt
pechenegi/c/34.txt
pechenegi/c/35.txt
pechenegi/c/36.txt
pechenegi/c/37.txt
pechenegi/c/39.txt
pechenegi/c/4.txt
pechenegi/c/40.txt
pechenegi/c/41.txt
pechenegi/c/42.txt
pechenegi/c/43.txt
pechenegi/c/44.txt
pechenegi/c/45.txt
pechenegi/c/47.txt
pechenegi/c/49.txt
pechenegi/c/49.txt~
pechenegi/c/5.txt
pechenegi/c/52.txt
pechenegi/c/53.txt
pechenegi/c/54.txt
pechenegi/c/55.txt
pechenegi/c/59.txt
pechenegi/c/6.txt
pechenegi/c/61.txt
pechenegi/c/63.txt
pechenegi/c/65.txt
pechenegi/c/7.txt
pechenegi/c/8.txt
pechenegi/c/9.txt
pechenegi/t/1.txt
pechenegi/t/10.txt
pechenegi/t/11.txt
pechenegi/t/12.txt
pechenegi/t/13.txt
pechenegi/t/14.txt
pechenegi/t/15.txt
pechenegi/t/16.txt
pechenegi/t/17.txt
pechenegi/t/18.txt
pechenegi/t/19.txt
pechenegi/t/2.txt
pechenegi/t/20.txt
pechenegi/t/21.txt
pechenegi/t/22.txt
pechenegi/t/23.txt
pechenegi/t/24.txt
pechenegi/t/25.txt
pechenegi/t/3.txt
pechenegi/t/4.txt
pechenegi/t/5.txt
pechenegi/t/6.txt
pechenegi/t/7.txt
pechenegi/t/8.txt
pechenegi/t/9.txt
pechenegi-2.9.dist-info/METADATA
pechenegi-2.9.dist-info/WHEEL
pechenegi-2.9.dist-info/licenses/LICENSE
pechenegi-2.9.dist-info/RECORD
