Metadata-Version: 2.1
Name: pechenegi
Version: 2.9
Summary: A Python library
Author-email: maria <masha@mail.ru>
License-File: LICENSE
Classifier: License :: OSI Approved :: MIT License
Classifier: Operating System :: OS Independent
Classifier: Programming Language :: Python :: 3
Requires-Python: >=3.9.0
